{
    "conditions": [
        {
            "type": "repurpose:config_recipe",
            "recipeKey": "Bag of Holding"
        }
    ],
    "type": "minecraft:crafting_shaped",
    "group": "Bag of Holding",
    "pattern": [
        "ADA",
        "BCB",
        "ABA"
    ],
    "key": {
        "A": [
            {
                "tag": "minecraft:wool"
            }
        ],
        "B": [
            {
                "item": "minecraft:leather"
            }
        ],
        "C": [
            {
                "item": "minecraft:ender_chest"
            }
        ],
        "D": [
            {
                "item": "minecraft:string"
            }
        ]
    },
    "result": {
        "item": "repurpose:item_bag_of_holding",
        "count": 1
    }
}
